{"index.js":"//Setup\nvar contacts = [\n    {\n        \"firstName\": \"Akira\",\n        \"lastName\": \"Laine\",\n        \"number\": \"0543236543\",\n        \"likes\": [\"Pizza\", \"Coding\", \"Brownie Points\"]\n    },\n    {\n        \"firstName\": \"Harry\",\n        \"lastName\": \"Potter\",\n        \"number\": \"0994372684\",\n        \"likes\": [\"Hogwarts\", \"Magic\", \"Hagrid\"]\n    },\n    {\n        \"firstName\": \"Sherlock\",\n        \"lastName\": \"Holmes\",\n        \"number\": \"0487345643\",\n        \"likes\": [\"Intriguing Cases\", \"Violin\"]\n    },\n    {\n        \"firstName\": \"Kristian\",\n        \"lastName\": \"Vos\",\n        \"number\": \"unknown\",\n        \"likes\": [\"JavaScript\", \"Gaming\", \"Foxes\"]\n    }\n];\n\n\nfunction lookUpProfile(name, prop){\n// Only change code below this line\nvar namecheck=0;\nfor(var i=0; i<=contacts.length-1; i++) {\nif (contacts[i].firstName === name) {\nnamecheck = 1;\n}\n}\nfor(var i=0;i<contacts.length;i++){\nif (contacts[i].firstName==name){\n//namecheck=1;\nif(contacts[i].hasOwnProperty(prop))\nreturn contacts[i][prop];\nelse\nreturn \"No such property\";\n}\nif (namecheck==0)\nreturn \"No such contact\";\n}\n// Only change code above this line\n}\n\n// Change these values to test your function\nlookUpProfile(\"Akira\", \"likes\");"}